swatpy/FileEdit.py
swatpy/ReadOut.py
swatpy/SimManage.py
swatpy/__init__.py
swatpy-0.2.0.dist-info/LICENSE
swatpy-0.2.0.dist-info/METADATA
swatpy-0.2.0.dist-info/WHEEL
swatpy-0.2.0.dist-info/top_level.txt
swatpy-0.2.0.dist-info/RECORD
